local_responder/__init__.py
local_responder-0.2.0.dist-info/WHEEL
local_responder-0.2.0.dist-info/METADATA
local_responder-0.2.0.dist-info/RECORD
