Metadata-Version: 2.1
Name: local-responder
Version: 0.2.0
Summary: A asynchronous temporary web server to repond to requests
Home-page: https://github.com/ikornaselur/local-responder
License: MIT
Author: Axel
Author-email: dev@absalon.is
Requires-Python: >=3.7,<4.0
Classifier: License :: OSI Approved :: MIT License
Classifier: Programming Language :: Python :: 3
Classifier: Programming Language :: Python :: 3.10
Classifier: Programming Language :: Python :: 3.7
Classifier: Programming Language :: Python :: 3.8
Classifier: Programming Language :: Python :: 3.9
Requires-Dist: aiohttp (>=3.7.4,<4.0.0)
